__init__.py
pyxtls/__init__.py
pyxtls/helpers/__init__.py
pyxtls/helpers/aes_crypt.py
pyxtls/helpers/collections.py
pyxtls/helpers/mappings.py
pyxtls-1.0.1.dist-info/LICENSE
pyxtls-1.0.1.dist-info/METADATA
pyxtls-1.0.1.dist-info/WHEEL
pyxtls-1.0.1.dist-info/entry_points.txt
pyxtls-1.0.1.dist-info/top_level.txt
pyxtls-1.0.1.dist-info/RECORD
